<?xml version="1.0" encoding="utf-8"?>
<cms.query>
  <ClassID>
    <CodeName>cms.WebFarmTask</CodeName>
    <GUID>44576ef8-a9b8-44e6-ba9d-4643f7de17cf</GUID>
    <ObjectType>cms.class</ObjectType>
  </ClassID>
  <QueryConnectionString>CMSConnectionString</QueryConnectionString>
  <QueryGUID>1e286bad-e69d-4d08-8329-4a72a522fb46</QueryGUID>
  <QueryIsCustom>False</QueryIsCustom>
  <QueryIsLocked>False</QueryIsLocked>
  <QueryName>selectForUnigrid</QueryName>
  <QueryRequiresTransaction>False</QueryRequiresTransaction>
  <QueryText>
    <![CDATA[SELECT ##TOPN## ##COLUMNS## FROM [CMS_WebFarmServer] INNER JOIN CMS_WebFarmServerTask ON CMS_WebFarmServerTask.ServerID = CMS_WebFarmServer.ServerID LEFT JOIN CMS_WebFarmTask ON CMS_WebFarmServerTask.TaskID = CMS_WebFarmTask.TaskID WHERE (##WHERE##) ORDER BY ##ORDERBY##]]>
  </QueryText>
  <QueryTypeID>0</QueryTypeID>
</cms.query>