<?xml version="1.0" encoding="utf-8"?>
<cms.alternativeform>
  <FormClassID>
    <CodeName>cms.class</CodeName>
    <GUID>d7e91104-201b-4b11-9550-e93ad9a4d81f</GUID>
    <ObjectType>cms.class</ObjectType>
  </FormClassID>
  <FormCustomizedColumns />
  <FormDefinition>
    <form version="2">
      <field column="ClassID" guid="15a00747-3ff0-470a-ae7a-cc99c8a8259f" isunique="true" />
      <field column="ClassDisplayName" guid="b622e4bc-00e4-4ddd-bc24-952579b9812a">
        <settings>
          <controlname>localizabletextbox</controlname>
          <ValueIsContent>False</ValueIsContent>
          <AutoCompleteEnableCaching />
          <AutoCompleteFirstRowSelected />
          <AutoCompleteShowOnlyCurrentWordInCompletionListItem />
          <FilterMode />
          <Trim />
        </settings>
        <properties>
          <fielddescription>{$customtable.classdisplayname.description$}</fielddescription>
        </properties>
      </field>
      <field column="ClassName" guid="11b3b0bd-6161-4ea6-b714-2249e4710ff3">
        <settings>
          <ResourcePrefix>customtable.edit</ResourcePrefix>
        </settings>
        <properties>
          <fielddescription>{$customtable.classname.description$}</fielddescription>
          <validationerrormessage />
        </properties>
      </field>
      <field column="ClassUsesVersioning" guid="2783d609-e427-4a6a-b58f-11309c662557" />
      <field column="ClassIsDocumentType" guid="9644486f-782f-4582-9b94-06d82ec99cd4" />
      <field column="ClassIsCoupledClass" guid="60b11243-38b5-40a5-b3e1-d722e717b11b" />
      <field column="ClassXmlSchema" guid="fa1ff4fd-b445-494b-9b34-538b978011c7" />
      <field column="ClassFormDefinition" guid="0e36af3b-04b5-477b-86d9-e4fedbb6acfd" />
      <field column="ClassNodeNameSource" guid="ce45ef8a-ba6d-40da-b437-88221a134f0a" />
      <field column="ClassTableName" guid="b211147b-2e77-4f0d-9546-e18990108532">
        <settings>
          <controlname>labelcontrol</controlname>
          <AutoCompleteEnableCaching />
          <AutoCompleteFirstRowSelected />
          <AutoCompleteShowOnlyCurrentWordInCompletionListItem />
          <FilterMode />
          <Trim />
        </settings>
        <properties>
          <fielddescription>{$customtable.classtablename.description$}</fielddescription>
          <visiblemacro ismacro="true">{%ClassIsCoupledClass%}</visiblemacro>
        </properties>
      </field>
      <field column="ClassInheritsFromClassID" guid="794296ec-5b04-40a2-a9ea-a802629e6839" order="10">
        <settings>
          <controlname />
        </settings>
        <properties>
          <fieldcaption>{$DocumentType.InheritsFrom$}</fieldcaption>
          <visiblemacro ismacro="true">{%ClassIsCoupledClass%}</visiblemacro>
        </properties>
      </field>
      <field column="ClassShowTemplateSelection" guid="9d6a6d71-0f1a-49f3-810c-40b830a5cba9" hasdependingfields="true" order="11">
        <settings>
          <controlname />
        </settings>
        <properties>
          <fieldcaption>{$DocumentType_Edit_General.TemplateSelection$}</fieldcaption>
        </properties>
      </field>
      <field column="ClassFormLayout" guid="32425d42-712b-48ad-92f2-ca7be3493456" order="12" />
      <field column="ClassShowAsSystemTable" guid="ad5fbd45-77ac-4ef6-8df7-823392ea0357" visible="" order="13" />
      <field column="ClassUsePublishFromTo" guid="f6c7434d-b4f5-4788-878b-af4b7a011066" order="14">
        <settings>
          <controlname />
        </settings>
        <properties>
          <fieldcaption>{$DocumentType_Edit_General.UsePublishFromTo$}</fieldcaption>
        </properties>
      </field>
      <field column="ClassSKUMappings" guid="db0a08d0-ec66-45e4-bd0a-c3d1f86ffb6a" order="15" />
      <field column="ClassIsMenuItemType" guid="de9eca79-f828-4a86-8df6-72d4b2e36265" order="16">
        <settings>
          <controlname />
        </settings>
        <properties>
          <fieldcaption>{$DocumentType_Edit_General.IsMenuItem$}</fieldcaption>
        </properties>
      </field>
      <field column="ClassNodeAliasSource" guid="9db135ca-2256-4812-96d3-c9bbc1b458d1" order="17" />
      <field column="ClassLastModified" guid="b0efc357-062e-4db3-a772-4761673faa81" order="18" />
      <field column="ClassGUID" guid="155ef725-c6a5-434f-90e6-f9a91f70d6cb" order="19" />
      <field column="ClassCreateSKU" guid="087f9b36-6d29-4336-8fed-567b370935eb" order="20" />
      <field column="ClassIsProduct" guid="90f0e42e-40a8-4d74-a144-482dade5a01a" order="21" />
      <field column="ClassIsCustomTable" guid="9d94c00d-128b-4ebb-b019-05c591605f79" order="22" />
      <field column="ClassShowColumns" guid="95ac260b-5d66-4bf5-a16b-af7313b642e0" order="23" />
      <field column="ClassSearchTitleColumn" guid="0ca33adc-5951-43e0-883b-2900618012f6" order="24" />
      <field column="ClassSearchContentColumn" guid="c01c8c30-6ad8-4e78-89ff-4444f30a39f2" order="25" />
      <field column="ClassSearchImageColumn" guid="bc7d25ab-93cf-4613-ab30-1ed8fd2fb380" order="26" />
      <field column="ClassSearchCreationDateColumn" guid="9e93f0c7-0ca3-427c-9fcd-0b268d042848" order="27" />
      <field column="ClassSearchSettings" guid="b9ce15ef-d968-4341-b39b-569fe442cb54" order="28" />
      <field column="ClassConnectionString" guid="81f850e0-0dbd-4298-aebf-3a73bdc3b8e4" visible="" order="29" />
      <field column="ClassSearchEnabled" guid="befeb58a-0af5-4775-8f92-b1a35b2a4917" order="30" />
      <field column="ClassSKUDefaultDepartmentName" guid="0d3e0544-4d03-46ca-ac2b-5121a526b5ae" order="31" />
      <field column="ClassSKUDefaultDepartmentID" guid="e3bb4e99-5d76-4936-957b-ec8379e5c6fe" order="32" />
      <field column="ClassContactMapping" guid="fa0aa943-e3ef-42a0-ade2-179a27fc184b" order="33" />
      <field column="ClassContactOverwriteEnabled" guid="04b3aee9-b470-45b2-9c5e-90932d09cc19" order="34" />
      <field column="ClassSKUDefaultProductType" guid="7fdff914-9f78-4512-ab6e-ce640de4cb3b" order="35" />
      <field column="ClassIsProductSection" guid="2ef6ca34-511f-4894-a139-9e5d74e8f82d" order="36" />
      <field column="ClassFormLayoutType" guid="1197ae53-0087-4e94-9b62-b8d4f3c46919" />
      <field column="ClassVersionGUID" guid="f27eb613-419e-48d4-9046-6828e5d8caab" />
      <field column="ClassDefaultObjectType" guid="87954ccc-9d86-4dcc-8e05-90dc7bbdfeb6" />
      <field column="ClassIsForm" guid="1dd5c069-4856-48dd-9938-030db613fe0b" />
      <field column="ClassResourceID" guid="e8581cf4-a56e-4daf-9dd4-ee3f0d8a15b2" visible="" />
      <field column="ClassCodeGenerationSettings" guid="5a8428f9-3212-4ad6-be4e-7fd96928f699" order="42" />
      <field column="ClassIconClass" guid="6db7bd4c-3a91-4f98-8540-a82a070677ff" order="43" />
      <field column="ClassCustomizedColumns" guid="aac1c1dd-6965-49a8-8e30-05a652fbbbe7" order="44" />
      <field column="ClassURLPattern" guid="00c00c0d-1627-4bab-864c-1a6b371b8636" />
      <field column="ClassUsesPageBuilder" guid="2462fa2a-d236-4a96-8b1e-a8b72d645290" />
      <field column="ClassIsNavigationItem" guid="21ad165c-3970-4270-9fbc-f8ec98c2d3c2" />
      <field column="ClassHasURL" guid="38ca89b0-abfb-482e-a0d7-be1ee50de0f9" />
    </form>
  </FormDefinition>
  <FormDisplayName>Custom table</FormDisplayName>
  <FormGUID>2c36b466-77ef-4500-92b6-6be1a14d780d</FormGUID>
  <FormHideNewParentFields>False</FormHideNewParentFields>
  <FormIsCustom>False</FormIsCustom>
  <FormName>CustomTable</FormName>
</cms.alternativeform>