<?xml version="1.0" encoding="utf-8"?>
<cms.helptopic>
  <HelpTopicGUID>9d78d601-5a1d-418c-9f5b-0a2f144f426b</HelpTopicGUID>
  <HelpTopicLink>discount_rules_config</HelpTopicLink>
  <HelpTopicName>Configure discount rules</HelpTopicName>
  <HelpTopicOrder>1</HelpTopicOrder>
  <HelpTopicUIElementID>
    <CodeName>Tools.Ecommerce.DiscountRules</CodeName>
    <GUID>1a72d539-3431-48b5-b284-36a6a59eb77d</GUID>
    <ObjectType>cms.uielement</ObjectType>
    <Parent>
      <CodeName>CMS.Ecommerce</CodeName>
      <GUID>684e021b-8b56-4cbf-8fd5-b7a791fd2dbc</GUID>
      <ObjectType>cms.resource</ObjectType>
    </Parent>
  </HelpTopicUIElementID>
</cms.helptopic>