<?xml version="1.0" encoding="utf-8"?>
<cms.helptopic>
  <HelpTopicGUID>fd8bfefc-28a4-4198-a1bc-6b15a12a981c</HelpTopicGUID>
  <HelpTopicLink>macro_rules_creating</HelpTopicLink>
  <HelpTopicName>Create macro rules</HelpTopicName>
  <HelpTopicOrder>1</HelpTopicOrder>
  <HelpTopicUIElementID>
    <CodeName>OrderRules</CodeName>
    <GUID>9beb50ea-45c8-422d-a2b3-84012d7d10f9</GUID>
    <ObjectType>cms.uielement</ObjectType>
    <Parent>
      <CodeName>CMS.Ecommerce</CodeName>
      <GUID>684e021b-8b56-4cbf-8fd5-b7a791fd2dbc</GUID>
      <ObjectType>cms.resource</ObjectType>
    </Parent>
  </HelpTopicUIElementID>
</cms.helptopic>