<?xml version="1.0" encoding="utf-8"?>
<cms.permission>
  <PermissionDescription>{$permissiondescription.emailmarketing.destroy$}</PermissionDescription>
  <PermissionDisplayInMatrix>True</PermissionDisplayInMatrix>
  <PermissionDisplayName>Destroy</PermissionDisplayName>
  <PermissionEditableByGlobalAdmin>False</PermissionEditableByGlobalAdmin>
  <PermissionGUID>8ce8b7ec-c27c-4b66-954c-3488f1043a68</PermissionGUID>
  <PermissionName>Destroy</PermissionName>
  <PermissionOrder>2</PermissionOrder>
  <ResourceID>
    <CodeName>CMS.Newsletter</CodeName>
    <GUID>82445572-642a-4f53-a411-063e5f4b63c0</GUID>
    <ObjectType>cms.resource</ObjectType>
  </ResourceID>
</cms.permission>