<?xml version="1.0" encoding="utf-8"?>
<cms.macrorule>
  <MacroRuleAvailability>0</MacroRuleAvailability>
  <MacroRuleCondition>
    <![CDATA[{_is}(CurrentDocument.DocumentCulture == "{culture}")]]>
  </MacroRuleCondition>
  <MacroRuleDescription>{$macrorule.cmscurrentpagecultureis.description$}</MacroRuleDescription>
  <MacroRuleDisplayName>Current page culture is</MacroRuleDisplayName>
  <MacroRuleEnabled>True</MacroRuleEnabled>
  <MacroRuleGUID>cb81d8e8-7529-4e3a-a28e-03fdb8e3fd50</MacroRuleGUID>
  <MacroRuleIsCustom>False</MacroRuleIsCustom>
  <MacroRuleName>CMSCurrentPageCultureIs</MacroRuleName>
  <MacroRuleParameters>
    <form version="2">
      <field column="culture" columnsize="100" columntype="text" guid="49114ac4-626f-4e68-b9c8-aeae22024175" visible="true">
        <properties>
          <fieldcaption>select culture</fieldcaption>
        </properties>
        <settings>
          <controlname>selectculture</controlname>
        </settings>
      </field>
      <field allowempty="true" column="_is" columnsize="100" columntype="text" guid="b88ada9c-b52a-4b8e-9850-885be0c2edf9" visible="true">
        <properties>
          <defaultvalue>;is</defaultvalue>
          <fieldcaption>select operation</fieldcaption>
        </properties>
        <settings>
          <controlname>macronegationoperator</controlname>
          <Options>
<![CDATA[
;is
!;is not
]]>
          </Options>
          <RepeatDirection>horizontal</RepeatDirection>
        </settings>
      </field>
    </form>
  </MacroRuleParameters>
  <MacroRuleRequiresContext>True</MacroRuleRequiresContext>
  <MacroRuleResourceName />
  <MacroRuleText>Current page culture {_is} {culture}</MacroRuleText>
</cms.macrorule>