<?xml version="1.0" encoding="utf-8"?>
<!-- This is a CI serialization file for Janis Joplin -->
<cms.documentlocalization>
  <DocumentContent />
  <DocumentCreatedByUserID>
    <CodeName>administrator</CodeName>
    <GUID>6415b8ce-8072-4bcd-8e48-9d7178b826b7</GUID>
    <ObjectType>cms.user</ObjectType>
  </DocumentCreatedByUserID>
  <DocumentCreatedWhen>2020-07-01 19:03:33Z</DocumentCreatedWhen>
  <DocumentCulture>en-US</DocumentCulture>
  <DocumentGUID>b28ee7ed-d33d-4ecd-86c1-4a940d10ffac</DocumentGUID>
  <DocumentInheritsStylesheet>True</DocumentInheritsStylesheet>
  <DocumentModifiedByUserID>
    <CodeName>administrator</CodeName>
    <GUID>6415b8ce-8072-4bcd-8e48-9d7178b826b7</GUID>
    <ObjectType>cms.user</ObjectType>
  </DocumentModifiedByUserID>
  <DocumentModifiedWhen>2020-07-01 19:03:33Z</DocumentModifiedWhen>
  <DocumentName>Janis Joplin</DocumentName>
  <DocumentNodeID>
    <CodeName>/Doctors/Janis-Joplin</CodeName>
    <GUID>8f76e4fe-2924-4abf-becf-b2e2f3d6d8b2</GUID>
    <ObjectType>cms.node</ObjectType>
    <Site>
      <CodeName>MedioClinic</CodeName>
      <GUID>a0b584aa-1500-4916-be09-2c77e508a468</GUID>
      <ObjectType>cms.site</ObjectType>
    </Site>
  </DocumentNodeID>
  <DocumentShowInMenu>True</DocumentShowInMenu>
</cms.documentlocalization>