<?xml version="1.0" encoding="utf-8"?>
<cms.formusercontrol>
  <UserControlCodeName>MetafileUploaderControl</UserControlCodeName>
  <UserControlDescription>
    <![CDATA[Provides an uploader of files from the file system.]]>
  </UserControlDescription>
  <UserControlDisplayName>Metafile uploader</UserControlDisplayName>
  <UserControlFileName>
    <![CDATA[~/CMSFormControls/Metafiles/MetaFileUploadControl.ascx]]>
  </UserControlFileName>
  <UserControlForBinary>False</UserControlForBinary>
  <UserControlForBoolean>False</UserControlForBoolean>
  <UserControlForDateTime>False</UserControlForDateTime>
  <UserControlForDecimal>False</UserControlForDecimal>
  <UserControlForDocAttachments>False</UserControlForDocAttachments>
  <UserControlForDocRelationships>False</UserControlForDocRelationships>
  <UserControlForFile>False</UserControlForFile>
  <UserControlForGuid>True</UserControlForGuid>
  <UserControlForInteger>False</UserControlForInteger>
  <UserControlForLongText>False</UserControlForLongText>
  <UserControlForText>True</UserControlForText>
  <UserControlGUID>ba6a95ca-e409-41d6-b2bb-430f16e30d3e</UserControlGUID>
  <UserControlIsSystem>True</UserControlIsSystem>
  <UserControlParameters>
    <form version="2">
      <field allowempty="true" column="ObjectCategory" columnsize="250" columntype="text" guid="45b67d43-00e3-4d64-80bf-51ec74197cc0" resolvedefaultvalue="False" visible="true">
        <properties>
          <fieldcaption>Metafile category</fieldcaption>
        </properties>
        <settings>
          <controlname>DropDownListControl</controlname>
          <DisplayActualValueAsItem>False</DisplayActualValueAsItem>
          <EditText>False</EditText>
          <Options>
<![CDATA[
FormLayout;{$administration.categorytype$}
Thumbnail;{$general.thumbnail$}
Icon;{$general.icon$}
Template;{$content.ui.propertiestemplate$}
Invoice;{$com.ui.ordersinvoice$}
Issue;{$om.activitydetails.newsletterissue$}
Image;{$avat.image$}
E-product;{$com.sku.eproduct$}
]]>
          </Options>
          <SortItems>False</SortItems>
        </settings>
      </field>
    </form>
  </UserControlParameters>
  <UserControlPriority>0</UserControlPriority>
  <UserControlShowInCustomTables>False</UserControlShowInCustomTables>
  <UserControlShowInDocumentTypes>False</UserControlShowInDocumentTypes>
  <UserControlShowInReports>False</UserControlShowInReports>
  <UserControlShowInSystemTables>False</UserControlShowInSystemTables>
  <UserControlShowInWebParts>False</UserControlShowInWebParts>
</cms.formusercontrol>