<?xml version="1.0" encoding="utf-8"?>
<cms.formusercontrol>
  <UserControlCodeName>Password</UserControlCodeName>
  <UserControlDescription>
    <![CDATA[Provides a text field for entering user account passwords. Masks input by displaying dots instead of the typed-in characters. Validates the input according to the site's Password policy settings (Settings -> Security & Membership -> Passwords). ]]>
  </UserControlDescription>
  <UserControlDisplayName>Password for users</UserControlDisplayName>
  <UserControlFileName>
    <![CDATA[~/CMSModules/Membership/FormControls/Passwords/Password.ascx]]>
  </UserControlFileName>
  <UserControlForBinary>False</UserControlForBinary>
  <UserControlForBoolean>False</UserControlForBoolean>
  <UserControlForDateTime>False</UserControlForDateTime>
  <UserControlForDecimal>False</UserControlForDecimal>
  <UserControlForDocAttachments>False</UserControlForDocAttachments>
  <UserControlForDocRelationships>False</UserControlForDocRelationships>
  <UserControlForFile>False</UserControlForFile>
  <UserControlForGuid>False</UserControlForGuid>
  <UserControlForInteger>False</UserControlForInteger>
  <UserControlForLongText>False</UserControlForLongText>
  <UserControlForText>True</UserControlForText>
  <UserControlGUID>2c1d7668-0a12-4a01-80b7-df9538386a91</UserControlGUID>
  <UserControlIsSystem>False</UserControlIsSystem>
  <UserControlParameters>
    <form version="2" />
  </UserControlParameters>
  <UserControlPriority>0</UserControlPriority>
  <UserControlShowInCustomTables>True</UserControlShowInCustomTables>
  <UserControlShowInDocumentTypes>False</UserControlShowInDocumentTypes>
  <UserControlShowInReports>False</UserControlShowInReports>
  <UserControlShowInSystemTables>True</UserControlShowInSystemTables>
  <UserControlShowInWebParts>True</UserControlShowInWebParts>
</cms.formusercontrol>