<?xml version="1.0" encoding="utf-8"?>
<documentfields.medioclinic.doctor>
  <BackdropPicture>3a78c8d0-c7f9-4c68-8c80-954031ea1653</BackdropPicture>
  <Biography>
    <![CDATA[El Dr. Vick tiene experiencia en medicina de emergencia y medicina general. Obtuvo su título en la <strong>Facultad de Medicina de la Universidad de Toronto</strong>. Prosiguió su interés en la cirugía menor y recibió su certificación de Cirujano General en el <strong>Royal College of Surgeons England</strong>. Dr. Vick disfruta de la construcción de relaciones que ofrece la práctica general y usa esto con un enfoque en la prevención de enfermedades. Fuera de la medicina, Dr. Vick participa regularmente en triatlones Ironman y disfruta pasar tiempo con su familia.]]>
  </Biography>
  <Degree>MD</Degree>
  <Specialty>
    <![CDATA[Médico general]]>
  </Specialty>
  <UserAccount>70</UserAccount>
</documentfields.medioclinic.doctor>