<?xml version="1.0" encoding="utf-8"?>
<reporting.report>
  <ReportAccess>0</ReportAccess>
  <ReportCategoryID>
    <CodeName>Orders</CodeName>
    <GUID>5332254f-ae4d-4dd3-bb05-76168dbbe374</GUID>
    <ObjectType>reporting.reportcategory</ObjectType>
  </ReportCategoryID>
  <ReportConnectionString />
  <ReportDisplayName>Number of orders by currency</ReportDisplayName>
  <ReportEnableSubscription>True</ReportEnableSubscription>
  <ReportGUID>b7cc93bb-98ce-4eeb-a2a3-44554177078d</ReportGUID>
  <ReportLayout>
<![CDATA[
%%control:ReportGraph?NumberOfOrdersByCurrency.graph%%<br />
<br />
%%control:ReportTable?NumberOfOrdersByCurrency.table%%
]]>
  </ReportLayout>
  <ReportName>NumberOfOrdersByCurrency</ReportName>
  <ReportParameters>
    <form version="2">
      <field allowempty="true" column="FromDate" columntype="datetime" guid="5e5e8694-d5f1-4687-a3f8-ca3c9388b595" visible="true">
        <properties>
          <fieldcaption>{$general.from$}</fieldcaption>
        </properties>
        <settings>
          <controlname>calendarcontrol</controlname>
          <DisplayNow>True</DisplayNow>
          <EditTime>False</EditTime>
          <TimeZoneType>inherit</TimeZoneType>
        </settings>
      </field>
      <field allowempty="true" column="ToDate" columntype="datetime" guid="ef57a98f-4fcd-4146-b0e3-b0fc46b99626" visible="true">
        <properties>
          <fieldcaption>{$general.to$}</fieldcaption>
        </properties>
        <settings>
          <controlname>calendarcontrol</controlname>
          <DisplayNow>True</DisplayNow>
          <EditTime>False</EditTime>
          <TimeZoneType>inherit</TimeZoneType>
        </settings>
      </field>
      <field column="OnlyPaid" columntype="boolean" guid="c948cb0b-fe4d-49ad-9c2a-ece8dba72c02" visible="true">
        <properties>
          <defaultvalue>false</defaultvalue>
          <fieldcaption>{$com.parameters.onlypaidorders$}</fieldcaption>
        </properties>
        <settings>
          <controlname>checkboxcontrol</controlname>
        </settings>
      </field>
    </form>
  </ReportParameters>
</reporting.report>