<?xml version="1.0" encoding="utf-8"?>
<cms.classpermission>
  <ClassID>
    <CodeName>MedioClinic.SiteSection</CodeName>
    <GUID>60b77a45-da65-430f-bf96-b9532efbc23c</GUID>
    <ObjectType>cms.documenttype</ObjectType>
  </ClassID>
  <PermissionDescription>{$permissiondescription.document.createanywhere$}</PermissionDescription>
  <PermissionDisplayInMatrix>True</PermissionDisplayInMatrix>
  <PermissionDisplayName>{$permissionnames.createanywhere$}</PermissionDisplayName>
  <PermissionGUID>66f2c1e2-1a0c-4507-936e-d85f7eca3f99</PermissionGUID>
  <PermissionName>Create</PermissionName>
  <PermissionOrder>4</PermissionOrder>
</cms.classpermission>