<?xml version="1.0" encoding="utf-8"?>
<cms.uielement>
  <ElementCaption>{$general.all$}</ElementCaption>
  <ElementCheckModuleReadPermission>True</ElementCheckModuleReadPermission>
  <ElementDisplayName>{$general.all$}</ElementDisplayName>
  <ElementFromVersion>8.0</ElementFromVersion>
  <ElementGUID>6355175d-03b2-426c-b0a7-942bb48e28e4</ElementGUID>
  <ElementIsCustom>False</ElementIsCustom>
  <ElementIsGlobalApplication>False</ElementIsGlobalApplication>
  <ElementIsMenu>False</ElementIsMenu>
  <ElementName>pageviews.all</ElementName>
  <ElementOrder>1</ElementOrder>
  <ElementParentID>
    <CodeName>PageViews</CodeName>
    <GUID>51833a7f-0546-47fb-8593-ef4d326a2a7c</GUID>
    <ObjectType>cms.uielement</ObjectType>
    <Parent>
      <CodeName>CMS.WebAnalytics</CodeName>
      <GUID>d3c82114-86f7-4aa9-8206-9b006100641c</GUID>
      <ObjectType>cms.resource</ObjectType>
    </Parent>
  </ElementParentID>
  <ElementRequiresGlobalAdminPriviligeLevel>False</ElementRequiresGlobalAdminPriviligeLevel>
  <ElementResourceID>
    <CodeName>CMS.WebAnalytics</CodeName>
    <GUID>d3c82114-86f7-4aa9-8206-9b006100641c</GUID>
    <ObjectType>cms.resource</ObjectType>
  </ElementResourceID>
  <ElementSize>0</ElementSize>
  <ElementTargetURL>
    <![CDATA[~/CMSModules/WebAnalytics/Tools/Analytics_Report.aspx?statCodeName=pageviews&dataCodeName=pageviews&reportCodeName=pageviews.yearreport;pageviews.monthreport;pageviews.weekreport;pageviews.dayreport;pageviews.hourreport&displaytitle=false]]>
  </ElementTargetURL>
  <ElementType>Url</ElementType>
</cms.uielement>