<?xml version="1.0" encoding="utf-8"?>
<cms.settingskey>
  <KeyCategoryID>
    <CodeName>CMS.Debug.SQL</CodeName>
    <ObjectType>cms.settingscategory</ObjectType>
  </KeyCategoryID>
  <KeyDefaultValue>False</KeyDefaultValue>
  <KeyDescription>{$settingskey.cmsdebugsqlconnections.description$}</KeyDescription>
  <KeyDisplayName>{$settingskey.cmsdebugsqlconnections$}</KeyDisplayName>
  <KeyExplanationText />
  <KeyGUID>ecc6a4a3-95c7-428e-b66e-b3322cbca679</KeyGUID>
  <KeyIsCustom>False</KeyIsCustom>
  <KeyIsGlobal>True</KeyIsGlobal>
  <KeyIsHidden>False</KeyIsHidden>
  <KeyName>CMSDebugSQLConnections</KeyName>
  <KeyOrder>5</KeyOrder>
  <KeyType>boolean</KeyType>
  <KeyValue>False</KeyValue>
</cms.settingskey>