<?xml version="1.0" encoding="utf-8"?>
<cms.settingskey>
  <KeyCategoryID>
    <CodeName>CMS.System.General</CodeName>
    <ObjectType>cms.settingscategory</ObjectType>
  </KeyCategoryID>
  <KeyDefaultValue>0</KeyDefaultValue>
  <KeyDescription>{$settingskey.cmshotfixdataversion.description$}</KeyDescription>
  <KeyDisplayName>{$settingskey.cmshotfixdataversion$}</KeyDisplayName>
  <KeyExplanationText />
  <KeyGUID>1b9c9cfc-994a-4fc5-9964-55ae2bd41226</KeyGUID>
  <KeyIsCustom>False</KeyIsCustom>
  <KeyIsGlobal>True</KeyIsGlobal>
  <KeyIsHidden>True</KeyIsHidden>
  <KeyName>CMSHotfixDataVersion</KeyName>
  <KeyOrder>12</KeyOrder>
  <KeyType>int</KeyType>
  <KeyValue>0</KeyValue>
</cms.settingskey>