<?xml version="1.0" encoding="utf-8"?>
<cms.settingskey>
  <KeyCategoryID>
    <CodeName>CMS.URL.ContentTreeRouting</CodeName>
    <ObjectType>cms.settingscategory</ObjectType>
  </KeyCategoryID>
  <KeyDefaultValue>True</KeyDefaultValue>
  <KeyDescription>
    <![CDATA[{$settingskey.cmshidelanguageprefixfordefaultcultureurl.description$}]]>
  </KeyDescription>
  <KeyDisplayName>
    <![CDATA[{$settingskey.cmshidelanguageprefixfordefaultcultureurl$}]]>
  </KeyDisplayName>
  <KeyExplanationText />
  <KeyGUID>fbec108c-ea6f-4fe1-98cc-525f0417ea42</KeyGUID>
  <KeyIsCustom>False</KeyIsCustom>
  <KeyIsGlobal>False</KeyIsGlobal>
  <KeyIsHidden>False</KeyIsHidden>
  <KeyName>CMSHideLanguagePrefixForDefaultCultureURL</KeyName>
  <KeyOrder>4</KeyOrder>
  <KeyType>boolean</KeyType>
  <KeyValue>True</KeyValue>
</cms.settingskey>