<?xml version="1.0" encoding="utf-8"?>
<cms.permission>
  <PermissionDescription>{$permissiondescription.eventlog.read$}</PermissionDescription>
  <PermissionDisplayInMatrix>True</PermissionDisplayInMatrix>
  <PermissionDisplayName>Read</PermissionDisplayName>
  <PermissionEditableByGlobalAdmin>False</PermissionEditableByGlobalAdmin>
  <PermissionGUID>faf6eee4-542c-428d-ac25-91e0e19d97f2</PermissionGUID>
  <PermissionName>Read</PermissionName>
  <PermissionOrder>1</PermissionOrder>
  <ResourceID>
    <CodeName>CMS.EventLog</CodeName>
    <GUID>ff8285c1-9d1a-49b3-8c9d-7502e1e533f7</GUID>
    <ObjectType>cms.resource</ObjectType>
  </ResourceID>
</cms.permission>