<?xml version="1.0" encoding="utf-8"?>
<cms.uielement>
  <ElementAccessCondition>
    <![CDATA[{%Rule("CurrentUser.IsAuthorizedPerResource(\"CMS.Staging\",\"ManageObjectsTasks\")", "<rules><r pos=\"0\" par=\"\" op=\"and\" n=\"Permission\" ><p n=\"module\"><t>CMS.Staging</t><v>CMS.Staging</v><r>false</r><d>select module</d><vt>text</vt></p><p n=\"permission\"><t>ManageObjectsTasks</t><v>ManageObjectsTasks</v><r>false</r><d>select permission</d><vt>text</vt></p></r></rules>")|(identity)GlobalAdministrator|(hash)1680f6c9b8c50d3e9f1df8ee7e98501c6be7e6d3dca6234208d52fc1db09691c%}]]>
  </ElementAccessCondition>
  <ElementCaption>{$contentstaging.objects$}</ElementCaption>
  <ElementCheckModuleReadPermission>False</ElementCheckModuleReadPermission>
  <ElementDisplayName>{$contentstaging.objects$}</ElementDisplayName>
  <ElementFromVersion>6.0</ElementFromVersion>
  <ElementGUID>f732cc5b-72c9-41c3-979a-ec122fd91079</ElementGUID>
  <ElementIconClass />
  <ElementIsCustom>False</ElementIsCustom>
  <ElementIsGlobalApplication>False</ElementIsGlobalApplication>
  <ElementIsMenu>False</ElementIsMenu>
  <ElementName>Objects</ElementName>
  <ElementOrder>4</ElementOrder>
  <ElementParentID>
    <CodeName>Staging</CodeName>
    <GUID>fec737ad-c051-4617-bbae-bf83a9d37751</GUID>
    <ObjectType>cms.uielement</ObjectType>
    <Parent>
      <CodeName>CMS.Staging</CodeName>
      <GUID>b1640241-8905-4845-ac9a-0301cb60cb63</GUID>
      <ObjectType>cms.resource</ObjectType>
    </Parent>
  </ElementParentID>
  <ElementProperties>
    <data>
      <category_name_custom>False</category_name_custom>
      <includejquery>False</includejquery>
      <displaybreadcrumbs>False</displaybreadcrumbs>
    </data>
  </ElementProperties>
  <ElementRequiresGlobalAdminPriviligeLevel>False</ElementRequiresGlobalAdminPriviligeLevel>
  <ElementResourceID>
    <CodeName>CMS.Staging</CodeName>
    <GUID>b1640241-8905-4845-ac9a-0301cb60cb63</GUID>
    <ObjectType>cms.resource</ObjectType>
  </ElementResourceID>
  <ElementSize>0</ElementSize>
  <ElementTargetURL>~/CMSModules/Staging/Tools/Objects/Frameset.aspx</ElementTargetURL>
  <ElementType>Url</ElementType>
</cms.uielement>